{
  "LocalizedLanguageName": "English",
  "LocalizedFileExplorerEntryName": "File Explore",
  "LocalizedDatabaseInspectEntryName": "Database Inspect",
  "LocalizedViewDebugEntryName": "View Debug",
  "LocalizedSendInfoEntryName": "Send Information",
  "LocalizedConsoleLogEntryName": "Console Log",
  "LocalizedFileExplorerTitle": "File Explore",
  "LocalizedDatabaseInspectTitle": "Database Inspect",
  "LocalizedSendInfoTitle": "Send Information",
  "LocalizedConsoleLogTitle": "Console Log",
  "LocalizedContextMenuOpen": "Open",
  "LocalizedContextMenuDownload": "Download",
  "LocalizedContextMenuDelete": "Delete",
  "LocalizedContextMenuRename": "Rename",
  "LocalizedContextMenuUpload": "Upload",
  "LocalizedContextMenuCreateDirectory": "New Directory",
  "LocalizedFileAttributeCreateTime": "Create Time",
  "LocalizedFileAttributeModificationTime": "Modified Time",
  "LocalizedFileAttributeFilePath": "Path",
  "LocalizedDBInspectDatabaseFilePath": "Database file path: ",
  "LocalizedDBInspectBrowseData": "Browse Data",
  "LocalizedDBInspectExecuteSQL": "Execute SQL",
  "LocalizedDBInspectDatabaseSchema": "Schema",
  "LocalizedDBInspectRefresh": "Refresh",
  "LocalizedDBInspectExecute": "Execute",
  "LocalizedDBInspectInputSQLStatement": "SQL statement",
  "LocalizedDBInspectErrorPromptEmptyStatement": "empty sql statement",
  "LocalizedDBInspectDBDisconnectedPromptHtml": "<p>There is no database connected. This can be solved by the following method.</p><p>Search the objective database file in <a href='/pages/file_explorer/file_explorer.html'>file explore</a>, and open it.</p>",
  "LocalizedSendInfoTextareaPlaceholder": "input and send contents to app",
  "LocalizedSendInfoSendButtonTitle": "Send",
  "LocalizedConsoleLogButtonTitleConnect": "Connect",
  "LocalizedConsoleLogButtonTitleDisconnect": "Disconnect",
  "LocalizedConsoleLogButtonTitleRefresh": "Refresh connection state",
  "LocalizedConsoleLogStateName": "State: ",
  "LocalizedConsoleLogStateDisconnected": "Disconnected",
  "LocalizedConsoleLogStateConnected": "Connected"
}
